odoo/addons/website_event_type_description/README.rst
odoo/addons/website_event_type_description/__init__.py
odoo/addons/website_event_type_description/__manifest__.py
odoo/addons/website_event_type_description/i18n/es.po
odoo/addons/website_event_type_description/i18n/it.po
odoo/addons/website_event_type_description/i18n/website_event_type_description.pot
odoo/addons/website_event_type_description/images/all.png
odoo/addons/website_event_type_description/images/seminars.png
odoo/addons/website_event_type_description/migrations/12.0.1.0.0/post-migration.py
odoo/addons/website_event_type_description/models/__init__.py
odoo/addons/website_event_type_description/models/event.py
odoo/addons/website_event_type_description/readme/CONTRIBUTORS.rst
odoo/addons/website_event_type_description/readme/DESCRIPTION.rst
odoo/addons/website_event_type_description/readme/ROADMAP.rst
odoo/addons/website_event_type_description/readme/USAGE.rst
odoo/addons/website_event_type_description/static/description/icon.png
odoo/addons/website_event_type_description/static/description/index.html
odoo/addons/website_event_type_description/views/event.xml
odoo/addons/website_event_type_description/views/event_type_view.xml
odoo12_addon_website_event_type_description-12.0.1.0.0.99.dev9.dist-info/METADATA
odoo12_addon_website_event_type_description-12.0.1.0.0.99.dev9.dist-info/WHEEL
odoo12_addon_website_event_type_description-12.0.1.0.0.99.dev9.dist-info/top_level.txt
odoo12_addon_website_event_type_description-12.0.1.0.0.99.dev9.dist-info/RECORD
